authentic/__init__.py
authentic/__main__.py
authentic/cli.py
authentic/config.py
authentic/entities.py
authentic/utils.py
authentic/backends/__init__.py
authentic/backends/basic.py
authentic/backends/jwt/__init__.py
authentic/backends/jwt/exceptions.py
authentic/backends/jwt/tokens.py
authentic/backends/jwt/usecases.py
authentic/usecases/__init__.py
authentic/usecases/core.py
authentic/usecases/helper.py
authentic/usecases/mfa.py
authentic-0.0.11.dist-info/AUTHORS.rst
authentic-0.0.11.dist-info/LICENSE
authentic-0.0.11.dist-info/METADATA
authentic-0.0.11.dist-info/WHEEL
authentic-0.0.11.dist-info/entry_points.txt
authentic-0.0.11.dist-info/top_level.txt
authentic-0.0.11.dist-info/RECORD
